tgreports/__init__.py
tgreports/log.conf
tgreports/main.py
tgreports-0.16.dist-info/LICENSE
tgreports-0.16.dist-info/METADATA
tgreports-0.16.dist-info/WHEEL
tgreports-0.16.dist-info/top_level.txt
tgreports-0.16.dist-info/RECORD
