Metadata-Version: 2.1
Name: tgreports
Version: 0.16
Summary: Reports and logs on Telegram
Home-page: https://github.com/chilleco/tgreports
Author: Alex Poloz
Author-email: alexypoloz@gmail.com
License: MIT
Project-URL: Source, https://github.com/chilleco/tgreports
Keywords: reports,logs,logging,notifications,alerts,Telegram
Classifier: Development Status :: 4 - Beta
Classifier: Environment :: Console
Classifier: Intended Audience :: Developers
Classifier: Topic :: Software Development :: Libraries :: Application Frameworks
Classifier: License :: OSI Approved :: MIT License
Classifier: Programming Language :: Python :: 3
Classifier: Operating System :: OS Independent
Requires-Python: >=3.7, <4
License-File: LICENSE
Requires-Dist: tgio
